crewai_fs_plus/__init__.py
crewai_fs_plus/base.py
crewai_fs_plus/directory_read_tool.py
crewai_fs_plus/exceptions.py
crewai_fs_plus/file_delete_tool.py
crewai_fs_plus/file_read_tool.py
crewai_fs_plus/file_write_tool.py
crewai_fs_plus-0.1.0.dist-info/licenses/LICENSE
crewai_fs_plus-0.1.0.dist-info/METADATA
crewai_fs_plus-0.1.0.dist-info/WHEEL
crewai_fs_plus-0.1.0.dist-info/top_level.txt
crewai_fs_plus-0.1.0.dist-info/RECORD
