Metadata-Version: 2.4
Name: crewai-fs-plus
Version: 0.1.0
Summary: Enhanced filesystem tools for CrewAI with whitelist/blacklist filtering and directory sandboxing
Author-email: Max Gfeller <max.gfeller@gmail.com>
License: MIT
Project-URL: Homepage, https://github.com/MaxGfeller/crewai-fs-plus
Project-URL: Repository, https://github.com/MaxGfeller/crewai-fs-plus
Project-URL: Issues, https://github.com/MaxGfeller/crewai-fs-plus/issues
Keywords: crewai,tools,filesystem,ai,agents
Classifier: Development Status :: 4 - Beta
Classifier: Intended Audience :: Developers
Classifier: License :: OSI Approved :: MIT License
Classifier: Operating System :: OS Independent
Classifier: Programming Language :: Python :: 3
Classifier: Programming Language :: Python :: 3.10
Classifier: Programming Language :: Python :: 3.11
Classifier: Programming Language :: Python :: 3.12
Classifier: Topic :: Software Development :: Libraries :: Python Modules
Requires-Python: >=3.10
License-File: LICENSE
Requires-Dist: crewai>=0.80.0
Requires-Dist: pydantic>=2.0
Provides-Extra: dev
Requires-Dist: pytest>=8.0; extra == "dev"
Requires-Dist: pytest-cov>=4.0; extra == "dev"
Requires-Dist: build>=1.0; extra == "dev"
Requires-Dist: twine>=5.0; extra == "dev"
Dynamic: license-file
